LICENSE
MANIFEST.in
README.rst
setup.cfg
setup.py
django_oauth_toolkit_hup.egg-info/PKG-INFO
django_oauth_toolkit_hup.egg-info/SOURCES.txt
django_oauth_toolkit_hup.egg-info/dependency_links.txt
django_oauth_toolkit_hup.egg-info/not-zip-safe
django_oauth_toolkit_hup.egg-info/requires.txt
django_oauth_toolkit_hup.egg-info/top_level.txt
oauth2_provider/__init__.py
oauth2_provider/admin.py
oauth2_provider/backends.py
oauth2_provider/compat.py
oauth2_provider/decorators.py
oauth2_provider/exceptions.py
oauth2_provider/forms.py
oauth2_provider/generators.py
oauth2_provider/middleware.py
oauth2_provider/models.py
oauth2_provider/oauth2_backends.py
oauth2_provider/oauth2_validators.py
oauth2_provider/settings.py
oauth2_provider/urls.py
oauth2_provider/validators.py
oauth2_provider/ext/__init__.py
oauth2_provider/ext/rest_framework/__init__.py
oauth2_provider/ext/rest_framework/authentication.py
oauth2_provider/ext/rest_framework/permissions.py
oauth2_provider/migrations/0001_initial.py
oauth2_provider/migrations/0002_adding_indexes.py
oauth2_provider/migrations/__init__.py
oauth2_provider/templates/404.html
oauth2_provider/templates/oauth2_provider/application_confirm_delete.html
oauth2_provider/templates/oauth2_provider/application_detail.html
oauth2_provider/templates/oauth2_provider/application_form.html
oauth2_provider/templates/oauth2_provider/application_list.html
oauth2_provider/templates/oauth2_provider/application_registration_form.html
oauth2_provider/templates/oauth2_provider/authorize.html
oauth2_provider/templates/oauth2_provider/base.html
oauth2_provider/tests/__init__.py
oauth2_provider/tests/models.py
oauth2_provider/tests/settings.py
oauth2_provider/tests/test_application_views.py
oauth2_provider/tests/test_auth_backends.py
oauth2_provider/tests/test_authorization_code.py
oauth2_provider/tests/test_client_credential.py
oauth2_provider/tests/test_decorators.py
oauth2_provider/tests/test_generator.py
oauth2_provider/tests/test_implicit.py
oauth2_provider/tests/test_mixins.py
oauth2_provider/tests/test_models.py
oauth2_provider/tests/test_oauth2_backends.py
oauth2_provider/tests/test_oauth2_validators.py
oauth2_provider/tests/test_password.py
oauth2_provider/tests/test_rest_framework.py
oauth2_provider/tests/test_scopes.py
