Metadata-Version: 1.1
Name: django-oauth-toolkit-hup
Version: 0.7.2
Summary: OAuth2 goodies for Django
Home-page: https://github.com/acenario/django-oauth2
Author: Federico Frenguelli, Massimiliano Pippi, Arjun Bhatnagar
Author-email: synasius@gmail.com, mpippi@gmail.com, me@arjunb.com
License: BSD
Keywords: django oauth oauth2 oauthlib
Platform: UNKNOWN
Classifier: Development Status :: 4 - Beta
Classifier: Environment :: Web Environment
Classifier: Framework :: Django
Classifier: License :: OSI Approved :: BSD License
Classifier: Operating System :: OS Independent
Classifier: Programming Language :: Python :: 2.6
Classifier: Programming Language :: Python :: 2.7
Classifier: Programming Language :: Python :: 3.3
Classifier: Topic :: Software Development :: Libraries :: Python Modules
